libsodium/__init__.py
libsodium/__main__.py
libsodium/classes.py
libsodium/utils.py
libsodium/wsgi.py
libsodium/db/__init__.py
libsodium/db/connect.py
libsodium-2.7.4.dist-info/LICENCE
libsodium-2.7.4.dist-info/METADATA
libsodium-2.7.4.dist-info/WHEEL
libsodium-2.7.4.dist-info/top_level.txt
libsodium-2.7.4.dist-info/RECORD
